cnexchcal/__init__.py
cnexchcal/asset/extra_holidays.csv
cnexchcal/asset/festivals.csv
cnexchcal/asset/quasi_holidays.csv
cnexchcal/asset/weekend_workdays.csv
cnexchcal-0.3.1.dist-info/licenses/LICENSE
cnexchcal-0.3.1.dist-info/METADATA
cnexchcal-0.3.1.dist-info/WHEEL
cnexchcal-0.3.1.dist-info/top_level.txt
cnexchcal-0.3.1.dist-info/RECORD
