Metadata-Version: 2.4
Name: cnexchcal
Version: 0.3.1
Summary: Exchange Calendars: issession, trade_date_range
Author-email: rhozhang <rhozhang@163.com>
License-Expression: MIT
Project-URL: Homepage, https://github.com/rhozhang/cnexchcal
Project-URL: Issues, https://github.com/rhozhang/cnexchcal/issues
Classifier: Programming Language :: Python :: 3
Classifier: Operating System :: OS Independent
Requires-Python: >=3.12
License-File: LICENSE
Requires-Dist: polars
Dynamic: license-file
